{
  "name": "bulbasaur",
  "types": [
    {
      "type": {
        "name": "grass"
      },
      "slot": 1
    },
    {
      "type": {
        "name": "poison"
      },
      "slot": 2
    }
  ],
  "stats": [
    {
      "stat": {
        "name": "hp"
      },
      "base_stat": 45
    },
    {
      "stat": {
        "name": "attack"
      },
      "base_stat": 49
    },
    {
      "stat": {
        "name": "defense"
      },
      "base_stat": 49
    },
    {
      "stat": {
        "name": "special-attack"
      },
      "base_stat": 65
    },
    {
      "stat": {
        "name": "special-defense"
      },
      "base_stat": 65
    },
    {
      "stat": {
        "name": "speed"
      },
      "base_stat": 45
    }
  ],
  "id": 1
}
